backtrader_bokeh/__init__.py
backtrader_bokeh/app.py
backtrader_bokeh/cds.py
backtrader_bokeh/clock.py
backtrader_bokeh/config.default.json
backtrader_bokeh/config.json
backtrader_bokeh/confighandler.py
backtrader_bokeh/figure.py
backtrader_bokeh/optbrowser.py
backtrader_bokeh/tab.py
backtrader_bokeh/utils.py
backtrader_bokeh/version.py
backtrader_bokeh/web.py
backtrader_bokeh/webapp.py
backtrader_bokeh/analyzer_tables/__init__.py
backtrader_bokeh/analyzer_tables/annualreturn.py
backtrader_bokeh/analyzer_tables/calmar.py
backtrader_bokeh/analyzer_tables/drawdown.py
backtrader_bokeh/analyzer_tables/leverage.py
backtrader_bokeh/analyzer_tables/periodstats.py
backtrader_bokeh/analyzer_tables/sharperatio.py
backtrader_bokeh/analyzer_tables/sqn.py
backtrader_bokeh/analyzer_tables/timereturn.py
backtrader_bokeh/analyzer_tables/tradeanalyzers.py
backtrader_bokeh/analyzer_tables/tradelist.py
backtrader_bokeh/analyzer_tables/transactions.py
backtrader_bokeh/analyzer_tables/vwr.py
backtrader_bokeh/analyzers/__init__.py
backtrader_bokeh/analyzers/plot.py
backtrader_bokeh/analyzers/recorder.py
backtrader_bokeh/analyzers/tradelist.py
backtrader_bokeh/feeds/__init__.py
backtrader_bokeh/feeds/fakefeed.py
backtrader_bokeh/helper/__init__.py
backtrader_bokeh/helper/bokeh.py
backtrader_bokeh/helper/cds_ops.py
backtrader_bokeh/helper/datatable.py
backtrader_bokeh/helper/label.py
backtrader_bokeh/helper/marker.py
backtrader_bokeh/helper/params.py
backtrader_bokeh/indicators/__init__.py
backtrader_bokeh/indicators/extraline.py
backtrader_bokeh/live/__init__.py
backtrader_bokeh/live/client.py
backtrader_bokeh/live/datahandler.py
backtrader_bokeh/plugin/__init__.py
backtrader_bokeh/plugin/annualreturn.py
backtrader_bokeh/plugin/bbroker.py
backtrader_bokeh/plugin/cerebro.py
backtrader_bokeh/plugin/logger.py
backtrader_bokeh/plugin/model.py
backtrader_bokeh/plugin/order.py
backtrader_bokeh/plugin/plot.py
backtrader_bokeh/plugin/writer.py
backtrader_bokeh/schemes/__init__.py
backtrader_bokeh-0.8.9.dist-info/LICENSE
backtrader_bokeh-0.8.9.dist-info/METADATA
backtrader_bokeh-0.8.9.dist-info/WHEEL
backtrader_bokeh-0.8.9.dist-info/top_level.txt
backtrader_bokeh-0.8.9.dist-info/RECORD
