Metadata-Version: 2.1
Name: backtrader-bokeh
Version: 0.8.9
Summary: Plotting package for Backtrader (Bokeh)
Home-page: https://github.com/iniself/backtrader_bokeh
Author: Metaer
Author-email: 
License: GNU General Public License v3 or later (GPLv3+)
Project-URL: Bug Tracker, https://github.com/iniself/backtrader_bokeh/issues
Project-URL: Documentation, https://github.com/iniself/backtrader_bokeh/wiki
Project-URL: Source Code, https://github.com/iniself/backtrader_bokeh
Project-URL: Demos, https://github.com/iniself/backtrader_bokeh/tree/gh-pages
Keywords: trading,development,finance,quant,backtrader,Bokeh
Platform: UNKNOWN
Classifier: Development Status :: 5 - Production/Stable
Classifier: Environment :: Console
Classifier: Intended Audience :: Developers
Classifier: Intended Audience :: Financial and Insurance Industry
Classifier: License :: OSI Approved :: GNU General Public License v3 or later (GPLv3+)
Classifier: Operating System :: OS Independent
Classifier: Programming Language :: Python
Classifier: Programming Language :: Python :: 3
Classifier: Programming Language :: Python :: 3.7
Classifier: Programming Language :: Python :: 3.8
Classifier: Programming Language :: Python :: 3.9
Classifier: Programming Language :: Python :: 3.10
Classifier: Programming Language :: Python :: 3.11
Classifier: Programming Language :: Python :: 3.12
Classifier: Topic :: Office/Business :: Financial
Classifier: Topic :: Software Development
Requires-Python: >=3.6
License-File: LICENSE
Requires-Dist: backtrader
Requires-Dist: bokeh (<3.0.0,>=2.4.3)
Requires-Dist: jinja2
Requires-Dist: pandas
Requires-Dist: matplotlib (~=3.2.2)
